wakatimer.py
wakatimer-2.0.2.dist-info/licenses/LICENSE
wakatimer-2.0.2.dist-info/METADATA
wakatimer-2.0.2.dist-info/WHEEL
wakatimer-2.0.2.dist-info/entry_points.txt
wakatimer-2.0.2.dist-info/top_level.txt
wakatimer-2.0.2.dist-info/RECORD
